podnet/__init__.py
podnet/podnet.py
podnet_rpi-0.1.0.dist-info/LICENSE
podnet_rpi-0.1.0.dist-info/METADATA
podnet_rpi-0.1.0.dist-info/WHEEL
podnet_rpi-0.1.0.dist-info/top_level.txt
podnet_rpi-0.1.0.dist-info/RECORD
