Metadata-Version: 2.1
Name: podnet-rpi
Version: 0.1.0
Summary: Client library for Raspberry Pi's for communicating with Podnet.
Home-page: https://github.com/Podnet/podnet_rpi
Author: Apoorva Singh
Author-email: apoorvasingh157@gmail.com
License: UNKNOWN
Platform: UNKNOWN
Classifier: Programming Language :: Python :: 3.6
Classifier: License :: OSI Approved :: MIT License
Classifier: Operating System :: POSIX :: Linux
Classifier: Development Status :: 4 - Beta
Requires-Python: >=3.6
